aiklyra/__init__.py
aiklyra/client.py
aiklyra/exceptions.py
aiklyra/models.py
aiklyra/graph/__init__.py
aiklyra/graph/processor.py
aiklyra/graph/utils.py
aiklyra/graph/filters/__init__.py
aiklyra/graph/filters/base_filter.py
aiklyra/graph/filters/filter_fr.py
aiklyra/graph/filters/filter_threshold.py
aiklyra/graph/filters/filter_topk.py
aiklyra/graph/graph_visualizers/__init__.py
aiklyra/graph/graph_visualizers/base_graph_visualizer.py
aiklyra/graph/graph_visualizers/interactive_graph_visualizer.py
aiklyra/graph/graph_visualizers/sankey_graph_visualizer.py
aiklyra/graph/graph_visualizers/static_graph_visualizer.py
tests/__init__.py
tests/test_client.py
tests/test_graph_processing.py
tests/test_visualization.py
Aiklyra-1.1.0.dist-info/LICENSE
Aiklyra-1.1.0.dist-info/METADATA
Aiklyra-1.1.0.dist-info/WHEEL
Aiklyra-1.1.0.dist-info/top_level.txt
Aiklyra-1.1.0.dist-info/RECORD
