Metadata-Version: 2.1
Name: Aiklyra
Version: 1.1.0
Summary: A Python client library for Aiklyra API
Home-page: https://github.com/aiklyra/aiklyra.git
Author: Aiklyra
Author-email: achref.benammar@ieee.org
License: Apache License 2.0
Classifier: License :: OSI Approved :: Apache Software License
Classifier: Programming Language :: Python :: 3
Classifier: Operating System :: OS Independent
Requires-Python: >=3.11
License-File: LICENSE
Requires-Dist: requests (>=2.25.1)
Requires-Dist: pydantic (>=1.8.2)
Requires-Dist: python-dotenv (>=0.15.0)
Requires-Dist: networkx (==3.4.2)
Requires-Dist: numpy (<2.0)
Requires-Dist: matplotlib (<=3.10.0)
Requires-Dist: pyvis (==0.3.2)
